NumSep/__init__.py
NumSep-0.0.1.dist-info/LICENSE.txt
NumSep-0.0.1.dist-info/METADATA
NumSep-0.0.1.dist-info/WHEEL
NumSep-0.0.1.dist-info/top_level.txt
NumSep-0.0.1.dist-info/RECORD
